urigui
