Metadata-Version: 2.1
Name: urigui
Version: 2.0.1
Summary: Utility CLI for submitting solutions to URI Online Judge.
Home-page: https://github.com/vininjr/uricli
Author: Marcus Vinicius
Author-email: viniips@hotmail.com
License: Apache 2.0
Platform: UNKNOWN
